pyzon/__init__.py
pyzon/failover_utils.py
pyzon/request_utils.py
pyzon/retry_utils.py
pyzon/supplier_utils.py
pyzon/time_utils.py
pyzon-0.0.2.dist-info/LICENSE
pyzon-0.0.2.dist-info/METADATA
pyzon-0.0.2.dist-info/WHEEL
pyzon-0.0.2.dist-info/top_level.txt
pyzon-0.0.2.dist-info/RECORD
